{
  "date": "2026-01-23",
  "generated_at": "2026-02-26T22:32:59.839372+00:00",
  "methodology_version": "1.0",
  "parameters": {
    "srisk_k": 0.08,
    "covar_quantile": 0.05,
    "covar_window_days": 252,
    "lrmes_horizon_days": 22,
    "lrmes_market_drop": 0.4,
    "mes_tail_pct": 0.05
  },
  "system_srisk_usd_bn": 2390.2039,
  "bank_count": 26,
  "banks": [
    {
      "bank_name": "Agricultural Bank of China",
      "region": "CN",
      "covar_index": "^HSI",
      "mes": -0.014862,
      "lrmes": 0.433302,
      "covar": -0.028236,
      "delta_covar": -0.010865,
      "covar_beta": 0.462864,
      "srisk_usd_bn": 0.0,
      "market_cap_usd_bn": 16490.629616,
      "debt_usd_bn": 44960.218,
      "srisk_share_pct": 0.0,
      "bank_id": "ABC"
    },
    {
      "bank_name": "Crédit Agricole",
      "region": "EU",
      "covar_index": "^STOXX50E",
      "mes": -0.018027,
      "lrmes": 0.651441,
      "covar": -0.027742,
      "delta_covar": -0.015929,
      "covar_beta": 0.709044,
      "srisk_usd_bn": 163.168836,
      "market_cap_usd_bn": 62.077246,
      "debt_usd_bn": 2288.443,
      "srisk_share_pct": 6.8266,
      "bank_id": "ACA"
    },
    {
      "bank_name": "Bank of America",
      "region": "US",
      "covar_index": "^GSPC",
      "mes": -0.03369,
      "lrmes": 0.823159,
      "covar": -0.025473,
      "delta_covar": -0.012566,
      "covar_beta": 0.497719,
      "srisk_usd_bn": 186.518262,
      "market_cap_usd_bn": 377.685079,
      "debt_usd_bn": 3099.564,
      "srisk_share_pct": 7.8034,
      "bank_id": "BAC"
    },
    {
      "bank_name": "Barclays",
      "region": "GB",
      "covar_index": "^FTSE",
      "mes": -0.038481,
      "lrmes": 0.950731,
      "covar": -0.015249,
      "delta_covar": -0.00925,
      "covar_beta": 0.300952,
      "srisk_usd_bn": 115.051447,
      "market_cap_usd_bn": 49.04,
      "debt_usd_bn": 1465.929,
      "srisk_share_pct": 4.8135,
      "bank_id": "BARC"
    },
    {
      "bank_name": "BBVA",
      "region": "EU",
      "covar_index": "^STOXX50E",
      "mes": -0.026049,
      "lrmes": 0.863841,
      "covar": -0.019906,
      "delta_covar": -0.011398,
      "covar_beta": 0.377287,
      "srisk_usd_bn": 46.164059,
      "market_cap_usd_bn": 140.964705,
      "debt_usd_bn": 797.778,
      "srisk_share_pct": 1.9314,
      "bank_id": "BBVA"
    },
    {
      "bank_name": "Bank of New York Mellon",
      "region": "US",
      "covar_index": "^GSPC",
      "mes": -0.025669,
      "lrmes": 0.795051,
      "covar": -0.027468,
      "delta_covar": -0.015811,
      "covar_beta": 0.650835,
      "srisk_usd_bn": 17.411856,
      "market_cap_usd_bn": 82.015231,
      "debt_usd_bn": 410.951,
      "srisk_share_pct": 0.7285,
      "bank_id": "BK"
    },
    {
      "bank_name": "BNP Paribas",
      "region": "EU",
      "covar_index": "^STOXX50E",
      "mes": -0.025043,
      "lrmes": 0.826199,
      "covar": -0.025587,
      "delta_covar": -0.013859,
      "covar_beta": 0.47356,
      "srisk_usd_bn": 194.363826,
      "market_cap_usd_bn": 115.704637,
      "debt_usd_bn": 2660.808,
      "srisk_share_pct": 8.1317,
      "bank_id": "BNP"
    },
    {
      "bank_name": "Bank of China",
      "region": "CN",
      "covar_index": "^HSI",
      "mes": -0.01749,
      "lrmes": 0.675787,
      "covar": -0.035438,
      "delta_covar": -0.019869,
      "covar_beta": 1.104956,
      "srisk_usd_bn": 0.0,
      "market_cap_usd_bn": 14097.695225,
      "debt_usd_bn": 34312.849,
      "srisk_share_pct": 0.0,
      "bank_id": "BOC"
    },
    {
      "bank_name": "Bank of Communications",
      "region": "CN",
      "covar_index": "^HSI",
      "mes": -0.010553,
      "lrmes": 0.557796,
      "covar": -0.036309,
      "delta_covar": -0.017284,
      "covar_beta": 1.059034,
      "srisk_usd_bn": 0.0,
      "market_cap_usd_bn": 5024.700382,
      "debt_usd_bn": 14130.635,
      "srisk_share_pct": 0.0,
      "bank_id": "BOCOM"
    },
    {
      "bank_name": "Groupe BPCE",
      "region": "EU",
      "covar_index": "^STOXX50E",
      "mes": -0.029654,
      "lrmes": 0.83095,
      "covar": -0.020771,
      "delta_covar": -0.00787,
      "covar_beta": 0.242086,
      "srisk_usd_bn": 107.785847,
      "market_cap_usd_bn": 61.618397,
      "debt_usd_bn": 1467.114,
      "srisk_share_pct": 4.5095,
      "bank_id": "BPCE"
    },
    {
      "bank_name": "Citigroup",
      "region": "US",
      "covar_index": "^GSPC",
      "mes": -0.04144,
      "lrmes": 0.906861,
      "covar": -0.026343,
      "delta_covar": -0.015447,
      "covar_beta": 0.452196,
      "srisk_usd_bn": 176.962717,
      "market_cap_usd_bn": 202.188851,
      "debt_usd_bn": 2428.598,
      "srisk_share_pct": 7.4037,
      "bank_id": "C"
    },
    {
      "bank_name": "China Construction Bank",
      "region": "CN",
      "covar_index": "^HSI",
      "mes": -0.014523,
      "lrmes": 0.605322,
      "covar": -0.026531,
      "delta_covar": -0.012137,
      "covar_beta": 0.643127,
      "srisk_usd_bn": 0.0,
      "market_cap_usd_bn": 15904.131286,
      "debt_usd_bn": 40847.989,
      "srisk_share_pct": 0.0,
      "bank_id": "CCB"
    },
    {
      "bank_name": "Deutsche Bank",
      "region": "EU",
      "covar_index": "^STOXX50E",
      "mes": -0.036107,
      "lrmes": 0.920614,
      "covar": -0.01997,
      "delta_covar": -0.008963,
      "covar_beta": 0.258626,
      "srisk_usd_bn": 99.595514,
      "market_cap_usd_bn": 73.853497,
      "debt_usd_bn": 1312.368,
      "srisk_share_pct": 4.1668,
      "bank_id": "DBK"
    },
    {
      "bank_name": "Société Générale",
      "region": "EU",
      "covar_index": "^STOXX50E",
      "mes": -0.029654,
      "lrmes": 0.83095,
      "covar": -0.020771,
      "delta_covar": -0.00787,
      "covar_beta": 0.242086,
      "srisk_usd_bn": 107.785847,
      "market_cap_usd_bn": 61.618397,
      "debt_usd_bn": 1467.114,
      "srisk_share_pct": 4.5095,
      "bank_id": "GLE"
    },
    {
      "bank_name": "Goldman Sachs",
      "region": "US",
      "covar_index": "^GSPC",
      "mes": -0.040364,
      "lrmes": 0.932045,
      "covar": -0.022889,
      "delta_covar": -0.012441,
      "covar_beta": 0.481391,
      "srisk_usd_bn": 117.295938,
      "market_cap_usd_bn": 278.164359,
      "debt_usd_bn": 1683.58,
      "srisk_share_pct": 4.9074,
      "bank_id": "GS"
    },
    {
      "bank_name": "HSBC Holdings",
      "region": "GB",
      "covar_index": "^FTSE",
      "mes": -0.029135,
      "lrmes": 0.866686,
      "covar": -0.013789,
      "delta_covar": -0.007706,
      "covar_beta": 0.29071,
      "srisk_usd_bn": 223.646658,
      "market_cap_usd_bn": 156.512943,
      "debt_usd_bn": 3035.535,
      "srisk_share_pct": 9.3568,
      "bank_id": "HSBC"
    },
    {
      "bank_name": "Industrial & Commercial Bank of China",
      "region": "CN",
      "covar_index": "^HSI",
      "mes": -0.011939,
      "lrmes": 0.526533,
      "covar": -0.028995,
      "delta_covar": -0.013586,
      "covar_beta": 0.771859,
      "srisk_usd_bn": 0.0,
      "market_cap_usd_bn": 21425.390736,
      "debt_usd_bn": 48179.055,
      "srisk_share_pct": 0.0,
      "bank_id": "ICBC"
    },
    {
      "bank_name": "ING Groep",
      "region": "EU",
      "covar_index": "^STOXX50E",
      "mes": -0.026907,
      "lrmes": 0.860022,
      "covar": -0.020005,
      "delta_covar": -0.009798,
      "covar_beta": 0.476967,
      "srisk_usd_bn": 69.689825,
      "market_cap_usd_bn": 82.204849,
      "debt_usd_bn": 1003.452,
      "srisk_share_pct": 2.9156,
      "bank_id": "ING"
    },
    {
      "bank_name": "JPMorgan Chase",
      "region": "US",
      "covar_index": "^GSPC",
      "mes": -0.03077,
      "lrmes": 0.83465,
      "covar": -0.027717,
      "delta_covar": -0.01563,
      "covar_beta": 0.626248,
      "srisk_usd_bn": 202.848997,
      "market_cap_usd_bn": 802.960482,
      "debt_usd_bn": 4062.462,
      "srisk_share_pct": 8.4867,
      "bank_id": "JPM"
    },
    {
      "bank_name": "Morgan Stanley",
      "region": "US",
      "covar_index": "^GSPC",
      "mes": -0.042359,
      "lrmes": 0.932107,
      "covar": -0.024427,
      "delta_covar": -0.015243,
      "covar_beta": 0.527741,
      "srisk_usd_bn": 82.628247,
      "market_cap_usd_bn": 282.926692,
      "debt_usd_bn": 1253.755,
      "srisk_share_pct": 3.457,
      "bank_id": "MS"
    },
    {
      "bank_name": "Banco Santander",
      "region": "EU",
      "covar_index": "^STOXX50E",
      "mes": -0.030037,
      "lrmes": 0.921102,
      "covar": -0.020502,
      "delta_covar": -0.012532,
      "covar_beta": 0.430055,
      "srisk_usd_bn": 127.259078,
      "market_cap_usd_bn": 180.781302,
      "debt_usd_bn": 1754.767,
      "srisk_share_pct": 5.3242,
      "bank_id": "SAN"
    },
    {
      "bank_name": "Standard Chartered",
      "region": "GB",
      "covar_index": "^FTSE",
      "mes": -0.034241,
      "lrmes": 0.804325,
      "covar": -0.012687,
      "delta_covar": -0.005591,
      "covar_beta": 0.218251,
      "srisk_usd_bn": 63.249184,
      "market_cap_usd_bn": 30.508106,
      "debt_usd_bn": 859.266,
      "srisk_share_pct": 2.6462,
      "bank_id": "STAN"
    },
    {
      "bank_name": "State Street",
      "region": "US",
      "covar_index": "^GSPC",
      "mes": -0.03512,
      "lrmes": 0.87127,
      "covar": -0.029332,
      "delta_covar": -0.019095,
      "covar_beta": 0.593391,
      "srisk_usd_bn": 23.30325,
      "market_cap_usd_bn": 35.218504,
      "debt_usd_bn": 343.428,
      "srisk_share_pct": 0.9749,
      "bank_id": "STT"
    },
    {
      "bank_name": "UBS Group",
      "region": "EU",
      "covar_index": "^STOXX50E",
      "mes": -0.035719,
      "lrmes": 0.832128,
      "covar": -0.02159,
      "delta_covar": -0.010363,
      "covar_beta": 0.375942,
      "srisk_usd_bn": 108.155809,
      "market_cap_usd_bn": 90.646267,
      "debt_usd_bn": 1526.943,
      "srisk_share_pct": 4.525,
      "bank_id": "UBS"
    },
    {
      "bank_name": "UniCredit",
      "region": "EU",
      "covar_index": "^STOXX50E",
      "mes": -0.029376,
      "lrmes": 0.906262,
      "covar": -0.021558,
      "delta_covar": -0.012719,
      "covar_beta": 0.403707,
      "srisk_usd_bn": 52.466366,
      "market_cap_usd_bn": 126.235627,
      "debt_usd_bn": 791.91,
      "srisk_share_pct": 2.1951,
      "bank_id": "UCG"
    },
    {
      "bank_name": "Wells Fargo",
      "region": "US",
      "covar_index": "^GSPC",
      "mes": -0.033976,
      "lrmes": 0.81777,
      "covar": -0.025533,
      "delta_covar": -0.014099,
      "covar_beta": 0.463047,
      "srisk_usd_bn": 104.852317,
      "market_cap_usd_bn": 271.639734,
      "debt_usd_bn": 1879.914,
      "srisk_share_pct": 4.3868,
      "bank_id": "WFC"
    }
  ]
}